word_embeddings_sdk/__init__.py
word_embeddings_sdk/api/__init__.py
word_embeddings_sdk/api/session.py
word_embeddings_sdk/domain/__init__.py
word_embeddings_sdk/domain/exceptions.py
word_embeddings_sdk/domain/models.py
word_embeddings_sdk/utils/__init__.py
word_embeddings_sdk/utils/utils.py
word_embeddings_sdk-0.1.5.dist-info/LICENSE
word_embeddings_sdk-0.1.5.dist-info/METADATA
word_embeddings_sdk-0.1.5.dist-info/WHEEL
word_embeddings_sdk-0.1.5.dist-info/top_level.txt
word_embeddings_sdk-0.1.5.dist-info/RECORD
