Metadata-Version: 2.1
Name: word-embeddings-sdk
Version: 0.1.5
Summary: Python sdk to interface with the WordEmbeddings API
Home-page: https://github.com/Width-ai/embeddings-sdk
Download-URL: https://github.com/Width-ai/embeddings-sdk/archive/refs/tags/v0.1.5.tar.gz
Author: Patrick Hennis
Author-email: patrick@width.ai
License: MIT
Keywords: Embeddings,SDK,WordEmbeddings,WordEmbeddings.Ai
Classifier: Development Status :: 3 - Alpha
Classifier: Intended Audience :: Developers
Classifier: Topic :: Software Development :: Build Tools
Classifier: License :: OSI Approved :: MIT License
Classifier: Programming Language :: Python :: 3
Classifier: Programming Language :: Python :: 3.6
Classifier: Programming Language :: Python :: 3.7
Classifier: Programming Language :: Python :: 3.8
Classifier: Programming Language :: Python :: 3.9
Classifier: Programming Language :: Python :: 3.10
License-File: LICENSE
Requires-Dist: requests (==2.31.0)
Requires-Dist: pydantic
